{"ObjectStates":[{"Transform":{"posX":0,"posY":1,"posZ":0,"rotX":0,"rotY":180,"rotZ":180,"scaleX":1,"scaleY":1,"scaleZ":1},"Name":"DeckCustom","ContainedObjects":[{"Name":"Card","Nickname":"Search for Azcanta // Azcanta, the Sunken Ruin","Transform":{"posX":0,"posY":0,"posZ":0,"rotX":0,"rotY":180,"rotZ":180,"scaleX":1,"scaleY":1,"scaleZ":1},"CardID":100},{"Name":"Card","Nickname":"Search for Azcanta // Azcanta, the Sunken Ruin","Transform":{"posX":0,"posY":0,"posZ":0,"rotX":0,"rotY":180,"rotZ":180,"scaleX":1,"scaleY":1,"scaleZ":1},"CardID":100},{"Name":"Card","Nickname":"Island","Transform":{"posX":0,"posY":0,"posZ":0,"rotX":0,"rotY":180,"rotZ":180,"scaleX":1,"scaleY":1,"scaleZ":1},"CardID":101},{"Name":"Card","Nickname":"Ritual of Soot","Transform":{"posX":0,"posY":0,"posZ":0,"rotX":0,"rotY":180,"rotZ":180,"scaleX":1,"scaleY":1,"scaleZ":1},"CardID":102},{"Name":"Card","Nickname":"Ritual of Soot","Transform":{"posX":0,"posY":0,"posZ":0,"rotX":0,"rotY":180,"rotZ":180,"scaleX":1,"scaleY":1,"scaleZ":1},"CardID":102},{"Name":"Card","Nickname":"Blood Crypt","Transform":{"posX":0,"posY":0,"posZ":0,"rotX":0,"rotY":180,"rotZ":180,"scaleX":1,"scaleY":1,"scaleZ":1},"CardID":103},{"Name":"Card","Nickname":"Blood Crypt","Transform":{"posX":0,"posY":0,"posZ":0,"rotX":0,"rotY":180,"rotZ":180,"scaleX":1,"scaleY":1,"scaleZ":1},"CardID":103},{"Name":"Card","Nickname":"Blood Crypt","Transform":{"posX":0,"posY":0,"posZ":0,"rotX":0,"rotY":180,"rotZ":180,"scaleX":1,"scaleY":1,"scaleZ":1},"CardID":103},{"Name":"Card","Nickname":"Blood Crypt","Transform":{"posX":0,"posY":0,"posZ":0,"rotX":0,"rotY":180,"rotZ":180,"scaleX":1,"scaleY":1,"scaleZ":1},"CardID":103},{"Name":"Card","Nickname":"Sulfur Falls","Transform":{"posX":0,"posY":0,"posZ":0,"rotX":0,"rotY":180,"rotZ":180,"scaleX":1,"scaleY":1,"scaleZ":1},"CardID":104},{"Name":"Card","Nickname":"Sulfur Falls","Transform":{"posX":0,"posY":0,"posZ":0,"rotX":0,"rotY":180,"rotZ":180,"scaleX":1,"scaleY":1,"scaleZ":1},"CardID":104},{"Name":"Card","Nickname":"Cry of the Carnarium","Transform":{"posX":0,"posY":0,"posZ":0,"rotX":0,"rotY":180,"rotZ":180,"scaleX":1,"scaleY":1,"scaleZ":1},"CardID":105},{"Name":"Card","Nickname":"Cry of the Carnarium","Transform":{"posX":0,"posY":0,"posZ":0,"rotX":0,"rotY":180,"rotZ":180,"scaleX":1,"scaleY":1,"scaleZ":1},"CardID":105},{"Name":"Card","Nickname":"Ugin, the Ineffable","Transform":{"posX":0,"posY":0,"posZ":0,"rotX":0,"rotY":180,"rotZ":180,"scaleX":1,"scaleY":1,"scaleZ":1},"CardID":106},{"Name":"Card","Nickname":"Nicol Bolas, the Ravager // Nicol Bolas, the Arisen","Transform":{"posX":0,"posY":0,"posZ":0,"rotX":0,"rotY":180,"rotZ":180,"scaleX":1,"scaleY":1,"scaleZ":1},"CardID":107},{"Name":"Card","Nickname":"Nicol Bolas, the Ravager // Nicol Bolas, the Arisen","Transform":{"posX":0,"posY":0,"posZ":0,"rotX":0,"rotY":180,"rotZ":180,"scaleX":1,"scaleY":1,"scaleZ":1},"CardID":107},{"Name":"Card","Nickname":"Nicol Bolas, the Ravager // Nicol Bolas, the Arisen","Transform":{"posX":0,"posY":0,"posZ":0,"rotX":0,"rotY":180,"rotZ":180,"scaleX":1,"scaleY":1,"scaleZ":1},"CardID":107},{"Name":"Card","Nickname":"Watery Grave","Transform":{"posX":0,"posY":0,"posZ":0,"rotX":0,"rotY":180,"rotZ":180,"scaleX":1,"scaleY":1,"scaleZ":1},"CardID":108},{"Name":"Card","Nickname":"Watery Grave","Transform":{"posX":0,"posY":0,"posZ":0,"rotX":0,"rotY":180,"rotZ":180,"scaleX":1,"scaleY":1,"scaleZ":1},"CardID":108},{"Name":"Card","Nickname":"Watery Grave","Transform":{"posX":0,"posY":0,"posZ":0,"rotX":0,"rotY":180,"rotZ":180,"scaleX":1,"scaleY":1,"scaleZ":1},"CardID":108},{"Name":"Card","Nickname":"Watery Grave","Transform":{"posX":0,"posY":0,"posZ":0,"rotX":0,"rotY":180,"rotZ":180,"scaleX":1,"scaleY":1,"scaleZ":1},"CardID":108},{"Name":"Card","Nickname":"Bedevil","Transform":{"posX":0,"posY":0,"posZ":0,"rotX":0,"rotY":180,"rotZ":180,"scaleX":1,"scaleY":1,"scaleZ":1},"CardID":109},{"Name":"Card","Nickname":"Bedevil","Transform":{"posX":0,"posY":0,"posZ":0,"rotX":0,"rotY":180,"rotZ":180,"scaleX":1,"scaleY":1,"scaleZ":1},"CardID":109},{"Name":"Card","Nickname":"Bedevil","Transform":{"posX":0,"posY":0,"posZ":0,"rotX":0,"rotY":180,"rotZ":180,"scaleX":1,"scaleY":1,"scaleZ":1},"CardID":109},{"Name":"Card","Nickname":"Bedevil","Transform":{"posX":0,"posY":0,"posZ":0,"rotX":0,"rotY":180,"rotZ":180,"scaleX":1,"scaleY":1,"scaleZ":1},"CardID":109},{"Name":"Card","Nickname":"Narset, Parter of Veils","Transform":{"posX":0,"posY":0,"posZ":0,"rotX":0,"rotY":180,"rotZ":180,"scaleX":1,"scaleY":1,"scaleZ":1},"CardID":110},{"Name":"Card","Nickname":"Narset, Parter of Veils","Transform":{"posX":0,"posY":0,"posZ":0,"rotX":0,"rotY":180,"rotZ":180,"scaleX":1,"scaleY":1,"scaleZ":1},"CardID":110},{"Name":"Card","Nickname":"Narset, Parter of Veils","Transform":{"posX":0,"posY":0,"posZ":0,"rotX":0,"rotY":180,"rotZ":180,"scaleX":1,"scaleY":1,"scaleZ":1},"CardID":110},{"Name":"Card","Nickname":"Narset, Parter of Veils","Transform":{"posX":0,"posY":0,"posZ":0,"rotX":0,"rotY":180,"rotZ":180,"scaleX":1,"scaleY":1,"scaleZ":1},"CardID":110},{"Name":"Card","Nickname":"Drowned Catacomb","Transform":{"posX":0,"posY":0,"posZ":0,"rotX":0,"rotY":180,"rotZ":180,"scaleX":1,"scaleY":1,"scaleZ":1},"CardID":111},{"Name":"Card","Nickname":"Drowned Catacomb","Transform":{"posX":0,"posY":0,"posZ":0,"rotX":0,"rotY":180,"rotZ":180,"scaleX":1,"scaleY":1,"scaleZ":1},"CardID":111},{"Name":"Card","Nickname":"Drowned Catacomb","Transform":{"posX":0,"posY":0,"posZ":0,"rotX":0,"rotY":180,"rotZ":180,"scaleX":1,"scaleY":1,"scaleZ":1},"CardID":111},{"Name":"Card","Nickname":"Drowned Catacomb","Transform":{"posX":0,"posY":0,"posZ":0,"rotX":0,"rotY":180,"rotZ":180,"scaleX":1,"scaleY":1,"scaleZ":1},"CardID":111},{"Name":"Card","Nickname":"Dragonskull Summit","Transform":{"posX":0,"posY":0,"posZ":0,"rotX":0,"rotY":180,"rotZ":180,"scaleX":1,"scaleY":1,"scaleZ":1},"CardID":112},{"Name":"Card","Nickname":"Dragonskull Summit","Transform":{"posX":0,"posY":0,"posZ":0,"rotX":0,"rotY":180,"rotZ":180,"scaleX":1,"scaleY":1,"scaleZ":1},"CardID":112},{"Name":"Card","Nickname":"Dragonskull Summit","Transform":{"posX":0,"posY":0,"posZ":0,"rotX":0,"rotY":180,"rotZ":180,"scaleX":1,"scaleY":1,"scaleZ":1},"CardID":112},{"Name":"Card","Nickname":"Dragonskull Summit","Transform":{"posX":0,"posY":0,"posZ":0,"rotX":0,"rotY":180,"rotZ":180,"scaleX":1,"scaleY":1,"scaleZ":1},"CardID":112},{"Name":"Card","Nickname":"Nicol Bolas, Dragon-God","Transform":{"posX":0,"posY":0,"posZ":0,"rotX":0,"rotY":180,"rotZ":180,"scaleX":1,"scaleY":1,"scaleZ":1},"CardID":113},{"Name":"Card","Nickname":"Nicol Bolas, Dragon-God","Transform":{"posX":0,"posY":0,"posZ":0,"rotX":0,"rotY":180,"rotZ":180,"scaleX":1,"scaleY":1,"scaleZ":1},"CardID":113},{"Name":"Card","Nickname":"The Elderspell","Transform":{"posX":0,"posY":0,"posZ":0,"rotX":0,"rotY":180,"rotZ":180,"scaleX":1,"scaleY":1,"scaleZ":1},"CardID":114},{"Name":"Card","Nickname":"The Elderspell","Transform":{"posX":0,"posY":0,"posZ":0,"rotX":0,"rotY":180,"rotZ":180,"scaleX":1,"scaleY":1,"scaleZ":1},"CardID":114},{"Name":"Card","Nickname":"Bedeck // Bedazzle","Transform":{"posX":0,"posY":0,"posZ":0,"rotX":0,"rotY":180,"rotZ":180,"scaleX":1,"scaleY":1,"scaleZ":1},"CardID":115},{"Name":"Card","Nickname":"Bedeck // Bedazzle","Transform":{"posX":0,"posY":0,"posZ":0,"rotX":0,"rotY":180,"rotZ":180,"scaleX":1,"scaleY":1,"scaleZ":1},"CardID":115},{"Name":"Card","Nickname":"Steam Vents","Transform":{"posX":0,"posY":0,"posZ":0,"rotX":0,"rotY":180,"rotZ":180,"scaleX":1,"scaleY":1,"scaleZ":1},"CardID":116},{"Name":"Card","Nickname":"Steam Vents","Transform":{"posX":0,"posY":0,"posZ":0,"rotX":0,"rotY":180,"rotZ":180,"scaleX":1,"scaleY":1,"scaleZ":1},"CardID":116},{"Name":"Card","Nickname":"Steam Vents","Transform":{"posX":0,"posY":0,"posZ":0,"rotX":0,"rotY":180,"rotZ":180,"scaleX":1,"scaleY":1,"scaleZ":1},"CardID":116},{"Name":"Card","Nickname":"Steam Vents","Transform":{"posX":0,"posY":0,"posZ":0,"rotX":0,"rotY":180,"rotZ":180,"scaleX":1,"scaleY":1,"scaleZ":1},"CardID":116},{"Name":"Card","Nickname":"Liliana, Dreadhorde General","Transform":{"posX":0,"posY":0,"posZ":0,"rotX":0,"rotY":180,"rotZ":180,"scaleX":1,"scaleY":1,"scaleZ":1},"CardID":117},{"Name":"Card","Nickname":"Thought Erasure","Transform":{"posX":0,"posY":0,"posZ":0,"rotX":0,"rotY":180,"rotZ":180,"scaleX":1,"scaleY":1,"scaleZ":1},"CardID":118},{"Name":"Card","Nickname":"Thought Erasure","Transform":{"posX":0,"posY":0,"posZ":0,"rotX":0,"rotY":180,"rotZ":180,"scaleX":1,"scaleY":1,"scaleZ":1},"CardID":118},{"Name":"Card","Nickname":"Thought Erasure","Transform":{"posX":0,"posY":0,"posZ":0,"rotX":0,"rotY":180,"rotZ":180,"scaleX":1,"scaleY":1,"scaleZ":1},"CardID":118},{"Name":"Card","Nickname":"Thought Erasure","Transform":{"posX":0,"posY":0,"posZ":0,"rotX":0,"rotY":180,"rotZ":180,"scaleX":1,"scaleY":1,"scaleZ":1},"CardID":118},{"Name":"Card","Nickname":"Hostage Taker","Transform":{"posX":0,"posY":0,"posZ":0,"rotX":0,"rotY":180,"rotZ":180,"scaleX":1,"scaleY":1,"scaleZ":1},"CardID":119},{"Name":"Card","Nickname":"Swamp","Transform":{"posX":0,"posY":0,"posZ":0,"rotX":0,"rotY":180,"rotZ":180,"scaleX":1,"scaleY":1,"scaleZ":1},"CardID":120},{"Name":"Card","Nickname":"Swamp","Transform":{"posX":0,"posY":0,"posZ":0,"rotX":0,"rotY":180,"rotZ":180,"scaleX":1,"scaleY":1,"scaleZ":1},"CardID":120},{"Name":"Card","Nickname":"Swamp","Transform":{"posX":0,"posY":0,"posZ":0,"rotX":0,"rotY":180,"rotZ":180,"scaleX":1,"scaleY":1,"scaleZ":1},"CardID":120},{"Name":"Card","Nickname":"Angrath's Rampage","Transform":{"posX":0,"posY":0,"posZ":0,"rotX":0,"rotY":180,"rotZ":180,"scaleX":1,"scaleY":1,"scaleZ":1},"CardID":121},{"Name":"Card","Nickname":"Angrath's Rampage","Transform":{"posX":0,"posY":0,"posZ":0,"rotX":0,"rotY":180,"rotZ":180,"scaleX":1,"scaleY":1,"scaleZ":1},"CardID":121},{"Name":"Card","Nickname":"Lava Coil","Transform":{"posX":0,"posY":0,"posZ":0,"rotX":0,"rotY":180,"rotZ":180,"scaleX":1,"scaleY":1,"scaleZ":1},"CardID":122},{"Name":"Card","Nickname":"Lava Coil","Transform":{"posX":0,"posY":0,"posZ":0,"rotX":0,"rotY":180,"rotZ":180,"scaleX":1,"scaleY":1,"scaleZ":1},"CardID":122}],"DeckIDs":[100,100,101,102,102,103,103,103,103,104,104,105,105,106,107,107,107,108,108,108,108,109,109,109,109,110,110,110,110,111,111,111,111,112,112,112,112,113,113,114,114,115,115,116,116,116,116,117,118,118,118,118,119,120,120,120,121,121,122,122],"CustomDeck":{"1":{"NumWidth":5,"NumHeight":5,"FaceURL":"https://www.frogtown.me/Shared/tts/deckAssets/v0/kwomtzkiybmueyzh0.jpg","BackURL":"https://www.frogtown.me/images/gatherer/CardBack.jpg"}}},{"Transform":{"posX":-4,"posY":1,"posZ":0,"rotX":0,"rotY":180,"rotZ":180,"scaleX":1,"scaleY":1,"scaleZ":1},"Name":"DeckCustom","ContainedObjects":[{"Name":"Card","Nickname":"Cry of the Carnarium","Transform":{"posX":0,"posY":0,"posZ":0,"rotX":0,"rotY":180,"rotZ":180,"scaleX":1,"scaleY":1,"scaleZ":1},"CardID":105},{"Name":"Card","Nickname":"The Elderspell","Transform":{"posX":0,"posY":0,"posZ":0,"rotX":0,"rotY":180,"rotZ":180,"scaleX":1,"scaleY":1,"scaleZ":1},"CardID":114},{"Name":"Card","Nickname":"The Elderspell","Transform":{"posX":0,"posY":0,"posZ":0,"rotX":0,"rotY":180,"rotZ":180,"scaleX":1,"scaleY":1,"scaleZ":1},"CardID":114},{"Name":"Card","Nickname":"Vraska's Contempt","Transform":{"posX":0,"posY":0,"posZ":0,"rotX":0,"rotY":180,"rotZ":180,"scaleX":1,"scaleY":1,"scaleZ":1},"CardID":123},{"Name":"Card","Nickname":"Vraska's Contempt","Transform":{"posX":0,"posY":0,"posZ":0,"rotX":0,"rotY":180,"rotZ":180,"scaleX":1,"scaleY":1,"scaleZ":1},"CardID":123},{"Name":"Card","Nickname":"Moment of Craving","Transform":{"posX":0,"posY":0,"posZ":0,"rotX":0,"rotY":180,"rotZ":180,"scaleX":1,"scaleY":1,"scaleZ":1},"CardID":300},{"Name":"Card","Nickname":"Duress","Transform":{"posX":0,"posY":0,"posZ":0,"rotX":0,"rotY":180,"rotZ":180,"scaleX":1,"scaleY":1,"scaleZ":1},"CardID":301},{"Name":"Card","Nickname":"Duress","Transform":{"posX":0,"posY":0,"posZ":0,"rotX":0,"rotY":180,"rotZ":180,"scaleX":1,"scaleY":1,"scaleZ":1},"CardID":301},{"Name":"Card","Nickname":"Hostage Taker","Transform":{"posX":0,"posY":0,"posZ":0,"rotX":0,"rotY":180,"rotZ":180,"scaleX":1,"scaleY":1,"scaleZ":1},"CardID":119},{"Name":"Card","Nickname":"Hostage Taker","Transform":{"posX":0,"posY":0,"posZ":0,"rotX":0,"rotY":180,"rotZ":180,"scaleX":1,"scaleY":1,"scaleZ":1},"CardID":119},{"Name":"Card","Nickname":"Ashiok, Dream Render","Transform":{"posX":0,"posY":0,"posZ":0,"rotX":0,"rotY":180,"rotZ":180,"scaleX":1,"scaleY":1,"scaleZ":1},"CardID":302},{"Name":"Card","Nickname":"Ashiok, Dream Render","Transform":{"posX":0,"posY":0,"posZ":0,"rotX":0,"rotY":180,"rotZ":180,"scaleX":1,"scaleY":1,"scaleZ":1},"CardID":302},{"Name":"Card","Nickname":"Enter the God-Eternals","Transform":{"posX":0,"posY":0,"posZ":0,"rotX":0,"rotY":180,"rotZ":180,"scaleX":1,"scaleY":1,"scaleZ":1},"CardID":303},{"Name":"Card","Nickname":"Enter the God-Eternals","Transform":{"posX":0,"posY":0,"posZ":0,"rotX":0,"rotY":180,"rotZ":180,"scaleX":1,"scaleY":1,"scaleZ":1},"CardID":303},{"Name":"Card","Nickname":"Enter the God-Eternals","Transform":{"posX":0,"posY":0,"posZ":0,"rotX":0,"rotY":180,"rotZ":180,"scaleX":1,"scaleY":1,"scaleZ":1},"CardID":303}],"DeckIDs":[105,114,114,123,123,300,301,301,119,119,302,302,303,303,303],"CustomDeck":{"1":{"NumWidth":5,"NumHeight":5,"FaceURL":"https://www.frogtown.me/Shared/tts/deckAssets/v0/kwomtzkiybmueyzh0.jpg","BackURL":"https://www.frogtown.me/images/gatherer/CardBack.jpg"},"3":{"NumWidth":5,"NumHeight":2,"FaceURL":"https://www.frogtown.me/Shared/tts/deckAssets/v0/kwomtzkiybmueyzh2.jpg","BackURL":"https://www.frogtown.me/images/gatherer/CardBack.jpg"}}},{"Transform":{"posX":-8,"posY":1,"posZ":0,"rotX":0,"rotY":180,"rotZ":180,"scaleX":1,"scaleY":1,"scaleZ":1},"Name":"DeckCustom","ContainedObjects":[{"Name":"Card","Nickname":"Spirit","Transform":{"posX":0,"posY":0,"posZ":0,"rotX":0,"rotY":180,"rotZ":180,"scaleX":1,"scaleY":1,"scaleZ":1},"CardID":304},{"Name":"Card","Nickname":"Zombie","Transform":{"posX":0,"posY":0,"posZ":0,"rotX":0,"rotY":180,"rotZ":180,"scaleX":1,"scaleY":1,"scaleZ":1},"CardID":305},{"Name":"Card","Nickname":"Zombie Army","Transform":{"posX":0,"posY":0,"posZ":0,"rotX":0,"rotY":180,"rotZ":180,"scaleX":1,"scaleY":1,"scaleZ":1},"CardID":306}],"DeckIDs":[304,305,306],"CustomDeck":{"3":{"NumWidth":5,"NumHeight":2,"FaceURL":"https://www.frogtown.me/Shared/tts/deckAssets/v0/kwomtzkiybmueyzh2.jpg","BackURL":"https://www.frogtown.me/images/gatherer/CardBack.jpg"}}},{"Transform":{"posX":-12,"posY":1,"posZ":0,"rotX":0,"rotY":180,"rotZ":180,"scaleX":1,"scaleY":1,"scaleZ":1},"Name":"DeckCustom","ContainedObjects":[{"Name":"Card","Nickname":"Search for Azcanta // Azcanta, the Sunken Ruin","Transform":{"posX":0,"posY":0,"posZ":0,"rotX":0,"rotY":180,"rotZ":180,"scaleX":1,"scaleY":1,"scaleZ":1},"CardID":9900},{"Name":"Card","Nickname":"Search for Azcanta // Azcanta, the Sunken Ruin","Transform":{"posX":0,"posY":0,"posZ":0,"rotX":0,"rotY":180,"rotZ":180,"scaleX":1,"scaleY":1,"scaleZ":1},"CardID":9900},{"Name":"Card","Nickname":"Nicol Bolas, the Ravager // Nicol Bolas, the Arisen","Transform":{"posX":0,"posY":0,"posZ":0,"rotX":0,"rotY":180,"rotZ":180,"scaleX":1,"scaleY":1,"scaleZ":1},"CardID":9901},{"Name":"Card","Nickname":"Nicol Bolas, the Ravager // Nicol Bolas, the Arisen","Transform":{"posX":0,"posY":0,"posZ":0,"rotX":0,"rotY":180,"rotZ":180,"scaleX":1,"scaleY":1,"scaleZ":1},"CardID":9901},{"Name":"Card","Nickname":"Nicol Bolas, the Ravager // Nicol Bolas, the Arisen","Transform":{"posX":0,"posY":0,"posZ":0,"rotX":0,"rotY":180,"rotZ":180,"scaleX":1,"scaleY":1,"scaleZ":1},"CardID":9901}],"DeckIDs":[9900,9900,9901,9901,9901],"CustomDeck":{"99":{"NumWidth":3,"NumHeight":1,"FaceURL":"https://www.frogtown.me/Shared/tts/deckAssets/v0/kwomtzkiybmueyzhflippable_front.jpg","UniqueBack":true,"BackURL":"https://www.frogtown.me/Shared/tts/deckAssets/v0/kwomtzkiybmueyzhflippable_back.jpg"}}}]}